{"seeds": [{"seed": 545, "data": {"HP": "296", "answer_2": "46755.34", "point_4x": "335", "point_4y": "67400", "__seed__": "0545"}}, {"seed": 851, "data": {"HP": "148", "answer_2": "21796.62", "point_4x": "335", "point_4y": "67400", "__seed__": "0851"}}, {"seed": 252, "data": {"HP": "361", "answer_2": "57716.94", "point_4x": "355", "point_4y": "52400", "__seed__": "0252"}}, {"seed": 468, "data": {"HP": "226", "answer_2": "34950.54", "point_4x": "300", "point_4y": "59000", "__seed__": "0468"}}, {"seed": 799, "data": {"HP": "352", "answer_2": "56199.18", "point_4x": "355", "point_4y": "52400", "__seed__": "0799"}}, {"seed": 612, "data": {"HP": "136", "answer_2": "19772.94", "point_4x": "187", "point_4y": "33700", "__seed__": "0612"}}, {"seed": 999, "data": {"HP": "166", "answer_2": "24832.14", "point_4x": "130", "point_4y": "14995", "__seed__": "0999"}}, {"seed": 138, "data": {"HP": "375", "answer_2": "60077.90", "point_4x": "355", "point_4y": "52400", "__seed__": "0138"}}, {"seed": 484, "data": {"HP": "271", "answer_2": "42539.34", "point_4x": "215", "point_4y": "35650", "__seed__": "0484"}}, {"seed": 99, "data": {"HP": "144", "answer_2": "21122.06", "point_4x": "187", "point_4y": "33700", "__seed__": "0099"}}], "generated_on": "2022-10-07T19:43:54.400650+00:00"}