{"seeds": [{"seed": 213, "data": {"high_1": "63.0", "sex_1": "woman", "answer_1": "-0.60", "sex_2": "male", "high_2": "71.0", "answer_2": "0.6306", "sex_3": "female", "dir_1": "taller", "min_max": "minimum", "percent_1": "46", "sex_4": "males", "answer_3": "64.2", "high_3": "67.4", "high_4": "73.2", "answer_4": "0.6639", "high_5": "67.6", "answer_5a": "0.2119", "answer_5b": "0.1075", "__seed__": "0213"}}, {"seed": 220, "data": {"high_1": "67.9", "sex_1": "man", "answer_1": "-0.70", "sex_2": "female", "high_2": "63.4", "answer_2": "0.3300", "sex_3": "male", "dir_1": "shorter", "min_max": "maximum", "percent_1": "42", "sex_4": "females", "answer_3": "70.6", "high_3": "62.5", "high_4": "68.0", "answer_4": "0.7074", "high_5": "67.3", "answer_5a": "0.1841", "answer_5b": "0.1314", "__seed__": "0220"}}, {"seed": 658, "data": {"high_1": "69.5", "sex_1": "man", "answer_1": "-0.17", "sex_2": "female", "high_2": "63.3", "answer_2": "0.3156", "sex_3": "male", "dir_1": "shorter", "min_max": "maximum", "percent_1": "45", "sex_4": "females", "answer_3": "70.4", "high_3": "61.1", "high_4": "65.9", "answer_4": "0.6253", "high_5": "68.1", "answer_5a": "0.2633", "answer_5b": "0.0749", "__seed__": "0658"}}, {"seed": 830, "data": {"high_1": "70.1", "sex_1": "woman", "answer_1": "2.24", "sex_2": "male", "high_2": "65.9", "answer_2": "0.0859", "sex_3": "female", "dir_1": "shorter", "min_max": "maximum", "percent_1": "55", "sex_4": "males", "answer_3": "64.2", "high_3": "66.6", "high_4": "72.8", "answer_4": "0.6961", "high_5": "68.7", "answer_5a": "0.3324", "answer_5b": "0.0465", "__seed__": "0830"}}, {"seed": 820, "data": {"high_1": "69.7", "sex_1": "man", "answer_1": "-0.10", "sex_2": "female", "high_2": "67.2", "answer_2": "0.8599", "sex_3": "male", "dir_1": "shorter", "min_max": "maximum", "percent_1": "44", "sex_4": "females", "answer_3": "70.5", "high_3": "61.7", "high_4": "66.9", "answer_4": "0.7001", "high_5": "67.7", "answer_5a": "0.2216", "answer_5b": "0.1003", "__seed__": "0820"}}, {"seed": 725, "data": {"high_1": "66.3", "sex_1": "man", "answer_1": "-1.23", "sex_2": "male", "high_2": "68.0", "answer_2": "0.2525", "sex_3": "female", "dir_1": "taller", "min_max": "minimum", "percent_1": "54", "sex_4": "females", "answer_3": "64.8", "high_3": "63.3", "high_4": "66.8", "answer_4": "0.5056", "high_5": "65.9", "answer_5a": "0.0859", "answer_5b": "0.2877", "__seed__": "0725"}}, {"seed": 527, "data": {"high_1": "70.8", "sex_1": "woman", "answer_1": "2.52", "sex_2": "male", "high_2": "72.9", "answer_2": "0.8331", "sex_3": "female", "dir_1": "shorter", "min_max": "maximum", "percent_1": "39", "sex_4": "males", "answer_3": "65.2", "high_3": "68.3", "high_4": "73.0", "answer_4": "0.5559", "high_5": "67.4", "answer_5a": "0.1931", "answer_5b": "0.1230", "__seed__": "0527"}}, {"seed": 38, "data": {"high_1": "62.3", "sex_1": "man", "answer_1": "-2.57", "sex_2": "male", "high_2": "70.4", "answer_2": "0.5530", "sex_3": "female", "dir_1": "taller", "min_max": "minimum", "percent_1": "58", "sex_4": "females", "answer_3": "65.0", "high_3": "62.2", "high_4": "68.6", "answer_4": "0.7707", "high_5": "66.0", "answer_5a": "0.0912", "answer_5b": "0.2743", "__seed__": "0038"}}, {"seed": 591, "data": {"high_1": "59.2", "sex_1": "woman", "answer_1": "-2.12", "sex_2": "male", "high_2": "72.7", "answer_2": "0.8159", "sex_3": "female", "dir_1": "taller", "min_max": "minimum", "percent_1": "35", "sex_4": "males", "answer_3": "63.5", "high_3": "68.7", "high_4": "72.1", "answer_4": "0.4257", "high_5": "68.8", "answer_5a": "0.3446", "answer_5b": "0.0427", "__seed__": "0591"}}, {"seed": 383, "data": {"high_1": "66.8", "sex_1": "man", "answer_1": "-1.07", "sex_2": "female", "high_2": "65.9", "answer_2": "0.7123", "sex_3": "male", "dir_1": "shorter", "min_max": "maximum", "percent_1": "60", "sex_4": "females", "answer_3": "69.2", "high_3": "61.0", "high_4": "68.5", "answer_4": "0.8644", "high_5": "68.5", "answer_5a": "0.3085", "answer_5b": "0.0548", "__seed__": "0383"}}], "generated_on": "2023-03-29T19:24:38.222828+00:00"}