{"seeds": [{"seed": 966, "data": {"sum": "-x^{4} - 6 \\, x^{4}", "result": "-7 \\, x^{4}", "__seed__": "0966"}}, {"seed": 479, "data": {"sum": "5 \\, x^{5} - 2 \\, x^{5}", "result": "3 \\, x^{5}", "__seed__": "0479"}}, {"seed": 848, "data": {"sum": "5 \\, x^{5} + 2 \\, x^{5}", "result": "7 \\, x^{5}", "__seed__": "0848"}}, {"seed": 716, "data": {"sum": "5 \\, x^{2} + 3 \\, x^{2}", "result": "8 \\, x^{2}", "__seed__": "0716"}}, {"seed": 902, "data": {"sum": "-x^{2} - 9 \\, x^{2}", "result": "-10 \\, x^{2}", "__seed__": "0902"}}, {"seed": 401, "data": {"sum": "6 \\, x^{4} - 7 \\, x^{4}", "result": "-x^{4}", "__seed__": "0401"}}, {"seed": 383, "data": {"sum": "-7 \\, x^{3}", "result": "-7 \\, x^{3}", "__seed__": "0383"}}, {"seed": 862, "data": {"sum": "4 \\, x^{4} - 8 \\, x^{4}", "result": "-4 \\, x^{4}", "__seed__": "0862"}}, {"seed": 648, "data": {"sum": "-4 \\, x^{2} - 8 \\, x^{2}", "result": "-12 \\, x^{2}", "__seed__": "0648"}}, {"seed": 969, "data": {"sum": "6 \\, x^{5} - 2 \\, x^{5}", "result": "4 \\, x^{5}", "__seed__": "0969"}}], "generated_on": "2024-11-30T20:14:49.615315+00:00"}