{"seeds": [{"seed": 58, "data": {"AA": "3", "var": "Color of helmet", "choice1": "Black", "choice2": "White", "choice3": "Red", "choice4": "Yellow", "choice5": "Total", "dep_var1": "Uninjured", "dep_var1_1": "411", "dep_var1_2": "315", "dep_var1_3": "174", "dep_var1_4": "289", "dep_var1_5": "1189", "dep_var2": "Injured", "dep_var2_1": "174", "dep_var2_2": "186", "dep_var2_3": "97", "dep_var2_4": "105", "dep_var2_5": "562", "dep_var3": "Killed", "dep_var3_1": "48", "dep_var3_2": "28", "dep_var3_3": "30", "dep_var3_4": "26", "dep_var3_5": "A", "total_title": "Total", "total_1": "633", "total_2": "529", "total_3": "301", "total_4": "B", "answer_a": "132", "answer_b": "420", "answer_c": "1883", "outcome_2": "Injured", "answer2_n": "562", "answer2": "0.2985", "color1": "Red", "color2": "Black", "answer3_1n": "301", "answer3_2n": "633", "answer3": "0.496", "hurt": "Uninjured", "color3": "White", "answer4_n": "315", "answer4_d": "1189", "answer4": "0.2649", "color4": "Yellow", "hurt2": "Uninjured", "answer5_n": "289", "answer5_d": "420", "answer5": "0.6881", "__seed__": "0058"}}, {"seed": 971, "data": {"AA": "2", "var": "Color of helmet", "choice1": "Black", "choice2": "White", "choice3": "Red", "choice4": "Yellow", "choice5": "Total", "dep_var1": "Uninjured", "dep_var1_1": "488", "dep_var1_2": "336", "dep_var1_3": "156", "dep_var1_4": "310", "dep_var1_5": "1290", "dep_var2": "Injured", "dep_var2_1": "212", "dep_var2_2": "193", "dep_var2_3": "114", "dep_var2_4": "125", "dep_var2_5": "A", "dep_var3": "Killed", "dep_var3_1": "51", "dep_var3_2": "52", "dep_var3_3": "16", "dep_var3_4": "32", "dep_var3_5": "151", "total_title": "Total", "total_1": "751", "total_2": "B", "total_3": "286", "total_4": "467", "answer_a": "644", "answer_b": "581", "answer_c": "2085", "outcome_2": "Killed", "answer2_n": "151", "answer2": "0.0724", "color1": "Black", "color2": "White", "answer3_1n": "751", "answer3_2n": "581", "answer3": "0.6388", "hurt": "Killed", "color3": "Yellow", "answer4_n": "32", "answer4_d": "151", "answer4": "0.2119", "color4": "Black", "hurt2": "Killed", "answer5_n": "51", "answer5_d": "751", "answer5": "0.0679", "__seed__": "0971"}}, {"seed": 853, "data": {"AA": "3", "var": "Color of helmet", "choice1": "Black", "choice2": "White", "choice3": "Red", "choice4": "Yellow", "choice5": "Total", "dep_var1": "Uninjured", "dep_var1_1": "417", "dep_var1_2": "246", "dep_var1_3": "169", "dep_var1_4": "282", "dep_var1_5": "1114", "dep_var2": "Injured", "dep_var2_1": "183", "dep_var2_2": "174", "dep_var2_3": "126", "dep_var2_4": "121", "dep_var2_5": "604", "dep_var3": "Killed", "dep_var3_1": "62", "dep_var3_2": "54", "dep_var3_3": "28", "dep_var3_4": "28", "dep_var3_5": "A", "total_title": "Total", "total_1": "662", "total_2": "474", "total_3": "B", "total_4": "431", "answer_a": "172", "answer_b": "323", "answer_c": "1890", "outcome_2": "Killed", "answer2_n": "172", "answer2": "0.091", "color1": "White", "color2": "Yellow", "answer3_1n": "474", "answer3_2n": "431", "answer3": "0.4788", "hurt": "Injured", "color3": "Yellow", "answer4_n": "121", "answer4_d": "604", "answer4": "0.2003", "color4": "White", "hurt2": "Uninjured", "answer5_n": "246", "answer5_d": "474", "answer5": "0.519", "__seed__": "0853"}}, {"seed": 759, "data": {"AA": "1", "var": "Color of helmet", "choice1": "Black", "choice2": "White", "choice3": "Red", "choice4": "Yellow", "choice5": "Total", "dep_var1": "Uninjured", "dep_var1_1": "383", "dep_var1_2": "253", "dep_var1_3": "106", "dep_var1_4": "296", "dep_var1_5": "A", "dep_var2": "Injured", "dep_var2_1": "212", "dep_var2_2": "135", "dep_var2_3": "113", "dep_var2_4": "162", "dep_var2_5": "622", "dep_var3": "Killed", "dep_var3_1": "67", "dep_var3_2": "28", "dep_var3_3": "25", "dep_var3_4": "34", "dep_var3_5": "154", "total_title": "Total", "total_1": "662", "total_2": "416", "total_3": "B", "total_4": "492", "answer_a": "1038", "answer_b": "244", "answer_c": "1814", "outcome_2": "Uninjured", "answer2_n": "1038", "answer2": "0.5722", "color1": "White", "color2": "Yellow", "answer3_1n": "416", "answer3_2n": "492", "answer3": "0.5006", "hurt": "Injured", "color3": "Black", "answer4_n": "212", "answer4_d": "622", "answer4": "0.3408", "color4": "White", "hurt2": "Killed", "answer5_n": "28", "answer5_d": "416", "answer5": "0.0673", "__seed__": "0759"}}, {"seed": 602, "data": {"AA": "2", "var": "Color of helmet", "choice1": "Black", "choice2": "White", "choice3": "Red", "choice4": "Yellow", "choice5": "Total", "dep_var1": "Uninjured", "dep_var1_1": "479", "dep_var1_2": "346", "dep_var1_3": "146", "dep_var1_4": "282", "dep_var1_5": "1253", "dep_var2": "Injured", "dep_var2_1": "212", "dep_var2_2": "111", "dep_var2_3": "77", "dep_var2_4": "92", "dep_var2_5": "A", "dep_var3": "Killed", "dep_var3_1": "51", "dep_var3_2": "64", "dep_var3_3": "20", "dep_var3_4": "31", "dep_var3_5": "166", "total_title": "Total", "total_1": "B", "total_2": "521", "total_3": "243", "total_4": "405", "answer_a": "492", "answer_b": "742", "answer_c": "1911", "outcome_2": "Uninjured", "answer2_n": "1253", "answer2": "0.6557", "color1": "Black", "color2": "White", "answer3_1n": "742", "answer3_2n": "521", "answer3": "0.6609", "hurt": "Uninjured", "color3": "Yellow", "answer4_n": "282", "answer4_d": "1253", "answer4": "0.2251", "color4": "Red", "hurt2": "Killed", "answer5_n": "20", "answer5_d": "243", "answer5": "0.0823", "__seed__": "0602"}}, {"seed": 724, "data": {"AA": "2", "var": "Color of helmet", "choice1": "Black", "choice2": "White", "choice3": "Red", "choice4": "Yellow", "choice5": "Total", "dep_var1": "Uninjured", "dep_var1_1": "386", "dep_var1_2": "264", "dep_var1_3": "131", "dep_var1_4": "219", "dep_var1_5": "1000", "dep_var2": "Injured", "dep_var2_1": "215", "dep_var2_2": "200", "dep_var2_3": "101", "dep_var2_4": "145", "dep_var2_5": "A", "dep_var3": "Killed", "dep_var3_1": "51", "dep_var3_2": "26", "dep_var3_3": "11", "dep_var3_4": "29", "dep_var3_5": "117", "total_title": "Total", "total_1": "652", "total_2": "490", "total_3": "B", "total_4": "393", "answer_a": "661", "answer_b": "243", "answer_c": "1778", "outcome_2": "Injured", "answer2_n": "661", "answer2": "0.3718", "color1": "Red", "color2": "Yellow", "answer3_1n": "243", "answer3_2n": "393", "answer3": "0.3577", "hurt": "Uninjured", "color3": "Yellow", "answer4_n": "219", "answer4_d": "1000", "answer4": "0.219", "color4": "Black", "hurt2": "Killed", "answer5_n": "51", "answer5_d": "652", "answer5": "0.0782", "__seed__": "0724"}}, {"seed": 820, "data": {"AA": "2", "var": "Color of helmet", "choice1": "Black", "choice2": "White", "choice3": "Red", "choice4": "Yellow", "choice5": "Total", "dep_var1": "Uninjured", "dep_var1_1": "397", "dep_var1_2": "370", "dep_var1_3": "154", "dep_var1_4": "152", "dep_var1_5": "1073", "dep_var2": "Injured", "dep_var2_1": "163", "dep_var2_2": "198", "dep_var2_3": "68", "dep_var2_4": "155", "dep_var2_5": "A", "dep_var3": "Killed", "dep_var3_1": "72", "dep_var3_2": "42", "dep_var3_3": "21", "dep_var3_4": "21", "dep_var3_5": "156", "total_title": "Total", "total_1": "632", "total_2": "610", "total_3": "243", "total_4": "B", "answer_a": "584", "answer_b": "328", "answer_c": "1813", "outcome_2": "Injured", "answer2_n": "584", "answer2": "0.3221", "color1": "Red", "color2": "White", "answer3_1n": "243", "answer3_2n": "610", "answer3": "0.4705", "hurt": "Killed", "color3": "White", "answer4_n": "42", "answer4_d": "156", "answer4": "0.2692", "color4": "Red", "hurt2": "Injured", "answer5_n": "68", "answer5_d": "243", "answer5": "0.2798", "__seed__": "0820"}}, {"seed": 270, "data": {"AA": "2", "var": "Color of helmet", "choice1": "Black", "choice2": "White", "choice3": "Red", "choice4": "Yellow", "choice5": "Total", "dep_var1": "Uninjured", "dep_var1_1": "404", "dep_var1_2": "363", "dep_var1_3": "101", "dep_var1_4": "285", "dep_var1_5": "1153", "dep_var2": "Injured", "dep_var2_1": "170", "dep_var2_2": "109", "dep_var2_3": "79", "dep_var2_4": "149", "dep_var2_5": "A", "dep_var3": "Killed", "dep_var3_1": "72", "dep_var3_2": "45", "dep_var3_3": "29", "dep_var3_4": "31", "dep_var3_5": "177", "total_title": "Total", "total_1": "646", "total_2": "B", "total_3": "209", "total_4": "465", "answer_a": "507", "answer_b": "517", "answer_c": "1837", "outcome_2": "Uninjured", "answer2_n": "1153", "answer2": "0.6277", "color1": "Black", "color2": "White", "answer3_1n": "646", "answer3_2n": "517", "answer3": "0.6331", "hurt": "Killed", "color3": "Red", "answer4_n": "29", "answer4_d": "177", "answer4": "0.1638", "color4": "Yellow", "hurt2": "Injured", "answer5_n": "149", "answer5_d": "465", "answer5": "0.3204", "__seed__": "0270"}}, {"seed": 406, "data": {"AA": "3", "var": "Color of helmet", "choice1": "Black", "choice2": "White", "choice3": "Red", "choice4": "Yellow", "choice5": "Total", "dep_var1": "Uninjured", "dep_var1_1": "426", "dep_var1_2": "220", "dep_var1_3": "215", "dep_var1_4": "241", "dep_var1_5": "1102", "dep_var2": "Injured", "dep_var2_1": "179", "dep_var2_2": "159", "dep_var2_3": "112", "dep_var2_4": "166", "dep_var2_5": "616", "dep_var3": "Killed", "dep_var3_1": "72", "dep_var3_2": "34", "dep_var3_3": "28", "dep_var3_4": "35", "dep_var3_5": "A", "total_title": "Total", "total_1": "B", "total_2": "413", "total_3": "355", "total_4": "442", "answer_a": "169", "answer_b": "677", "answer_c": "1887", "outcome_2": "Killed", "answer2_n": "169", "answer2": "0.0896", "color1": "White", "color2": "Yellow", "answer3_1n": "413", "answer3_2n": "442", "answer3": "0.4531", "hurt": "Uninjured", "color3": "Yellow", "answer4_n": "241", "answer4_d": "1102", "answer4": "0.2187", "color4": "Red", "hurt2": "Injured", "answer5_n": "112", "answer5_d": "355", "answer5": "0.3155", "__seed__": "0406"}}, {"seed": 360, "data": {"AA": "3", "var": "Color of helmet", "choice1": "Black", "choice2": "White", "choice3": "Red", "choice4": "Yellow", "choice5": "Total", "dep_var1": "Uninjured", "dep_var1_1": "387", "dep_var1_2": "262", "dep_var1_3": "183", "dep_var1_4": "279", "dep_var1_5": "1111", "dep_var2": "Injured", "dep_var2_1": "199", "dep_var2_2": "113", "dep_var2_3": "104", "dep_var2_4": "77", "dep_var2_5": "493", "dep_var3": "Killed", "dep_var3_1": "64", "dep_var3_2": "53", "dep_var3_3": "10", "dep_var3_4": "28", "dep_var3_5": "A", "total_title": "Total", "total_1": "650", "total_2": "428", "total_3": "B", "total_4": "384", "answer_a": "155", "answer_b": "297", "answer_c": "1759", "outcome_2": "Killed", "answer2_n": "155", "answer2": "0.0881", "color1": "Yellow", "color2": "White", "answer3_1n": "384", "answer3_2n": "428", "answer3": "0.4616", "hurt": "Injured", "color3": "Black", "answer4_n": "199", "answer4_d": "493", "answer4": "0.4037", "color4": "Red", "hurt2": "Killed", "answer5_n": "10", "answer5_d": "297", "answer5": "0.0337", "__seed__": "0360"}}], "generated_on": "2024-10-14T14:38:19.801716+00:00"}