{"seeds": [{"seed": 566, "data": {"population": "807", "sample": "468", "result": "9", "__seed__": "0566"}}, {"seed": 572, "data": {"population": "1087", "sample": "564", "result": "17", "__seed__": "0572"}}, {"seed": 17, "data": {"population": "980", "sample": "564", "result": "12", "__seed__": "0017"}}, {"seed": 159, "data": {"population": "894", "sample": "515", "result": "15", "__seed__": "0159"}}, {"seed": 967, "data": {"population": "888", "sample": "487", "result": "6", "__seed__": "0967"}}, {"seed": 93, "data": {"population": "796", "sample": "578", "result": "16", "__seed__": "0093"}}, {"seed": 757, "data": {"population": "774", "sample": "542", "result": "17", "__seed__": "0757"}}, {"seed": 991, "data": {"population": "818", "sample": "466", "result": "13", "__seed__": "0991"}}, {"seed": 486, "data": {"population": "1003", "sample": "459", "result": "10", "__seed__": "0486"}}, {"seed": 742, "data": {"population": "870", "sample": "564", "result": "7", "__seed__": "0742"}}], "generated_on": "2024-01-14T15:12:03.582705+00:00"}